cil_estimator/__init__.py
cil_estimator/objective_function.py
cil_estimator/plot.py
cil_estimator-0.1.0.dist-info/METADATA
cil_estimator-0.1.0.dist-info/WHEEL
cil_estimator-0.1.0.dist-info/top_level.txt
cil_estimator-0.1.0.dist-info/RECORD
