Metadata-Version: 2.1
Name: cil-estimator
Version: 0.1.0
Summary: Python package for parameter estimation of random data
Home-page: https://github.com/AndreasRupp/cil_estimator
Author: Andreas Rupp
Author-email: Andreas Rupp <info@rupp.ink>
License: LGPL-2.1
Project-URL: Homepage, https://github.com/AndreasRupp/ecdf_estimator
Project-URL: Bug Tracker, https://github.com/AndreasRupp/ecdf_estimator/issues
Classifier: Programming Language :: Python :: 3
Classifier: License :: OSI Approved :: GNU Lesser General Public License v2 or later (LGPLv2+)
Classifier: Operating System :: OS Independent
Requires-Python: >=3.8
Requires-Dist: numpy (>=1.19.5)
Requires-Dist: matplotlib (>=3.6)
